{"lastUsed":1629697956213,"path":"E:\/github\/spring\/AuctionSearch\/springBoot","projectCount":1,"recentFiles":[{"path":"\/SpringBootTest\/src\/main\/java\/com\/example\/demo","parentWorkspace":"E:\/SpringDev\/springBoot","name":"HomeController.java","lastModified":1628557041982,"locationURI":"file:\/E:\/SpringDev\/springBoot\/SpringBootTest\/src\/main\/java\/com\/example\/demo\/HomeController.java"},{"path":"\/SpringBootTest\/src\/main\/webapp\/WEB-INF\/views","parentWorkspace":"E:\/SpringDev\/springBoot","name":"auctionSearchMain.jsp","lastModified":1629677659380,"locationURI":"file:\/E:\/SpringDev\/springBoot\/SpringBootTest\/src\/main\/webapp\/WEB-INF\/views\/auctionSearchMain.jsp"},{"path":"\/SpringBootTest\/src\/main\/java\/com\/example\/demo","parentWorkspace":"E:\/SpringDev\/springBoot","name":"SpringBootTestApplication.java","lastModified":1628064841379,"locationURI":"file:\/E:\/SpringDev\/springBoot\/SpringBootTest\/src\/main\/java\/com\/example\/demo\/SpringBootTestApplication.java"},{"path":"\/SpringBootTest\/src\/main\/resources","parentWorkspace":"E:\/SpringDev\/springBoot","name":"application.properties","lastModified":1628559965516,"locationURI":"file:\/E:\/SpringDev\/springBoot\/SpringBootTest\/src\/main\/resources\/application.properties"},{"path":"\/SpringBootTest\/src\/main\/webapp\/resources\/js","parentWorkspace":"E:\/SpringDev\/springBoot","name":"Auction.js","lastModified":1628559785411,"locationURI":"file:\/E:\/SpringDev\/springBoot\/SpringBootTest\/src\/main\/webapp\/resources\/js\/Auction.js"},{"path":"\/SpringBootTest\/src\/main\/java\/com\/example\/demo","parentWorkspace":"E:\/SpringDev\/springBoot","name":"GetAuctionDataController.java","lastModified":1629697957108,"locationURI":"file:\/E:\/SpringDev\/springBoot\/SpringBootTest\/src\/main\/java\/com\/example\/demo\/GetAuctionDataController.java"},{"path":"\/SpringBootTest","parentWorkspace":"E:\/SpringDev\/springBoot","name":"pom.xml","lastModified":1628489013536,"locationURI":"file:\/E:\/SpringDev\/springBoot\/SpringBootTest\/pom.xml"}]}